README.rst
setup.py
setupreader.py
setupreader.egg-info/PKG-INFO
setupreader.egg-info/SOURCES.txt
setupreader.egg-info/dependency_links.txt
setupreader.egg-info/entry_points.txt
setupreader.egg-info/not-zip-safe
setupreader.egg-info/requires.txt
setupreader.egg-info/top_level.txt