Metadata-Version: 1.0
Name: setupreader
Version: 0.0.3
Summary: retrieve package specification from setup.py
Home-page: https://github.com/specialunderwear/setupreader
Author: Lars van de Kerkhof
Author-email: lars@permanentmarkers.nl
License: GPL
Platform: UNKNOWN
